./.gitignore
./CONTRIBUTING.md
./LICENSE
./PKG-INFO
./README.md
./bible_api.py
./bible_data.py
./bible_server.py
./pyproject.toml
./tests/test_bible_api.py
./tests/test_bible_data.py
./tests/test_bible_server.py
bible_mcp-1.0.0.dist-info/METADATA
bible_mcp-1.0.0.dist-info/WHEEL
bible_mcp-1.0.0.dist-info/entry_points.txt
bible_mcp-1.0.0.dist-info/licenses/LICENSE
bible_mcp-1.0.0.dist-info/RECORD
