Metadata-Version: 2.4
Name: bible-mcp
Version: 1.0.0
Summary: Model Context Protocol (MCP) server for Bible content
Project-URL: Homepage, https://github.com/trevato/bible-mcp
Project-URL: Documentation, https://github.com/trevato/bible-mcp#readme
Project-URL: Repository, https://github.com/trevato/bible-mcp.git
Project-URL: Issues, https://github.com/trevato/bible-mcp/issues
Author-email: trevato <contact@trevato.dev>
Maintainer-email: trevato <contact@trevato.dev>
License: MIT License
License-File: LICENSE
Keywords: ai,bible,claude,llm,mcp
Classifier: Development Status :: 4 - Beta
Classifier: Intended Audience :: Developers
Classifier: License :: OSI Approved :: MIT License
Classifier: Programming Language :: Python :: 3
Classifier: Programming Language :: Python :: 3.9
Classifier: Programming Language :: Python :: 3.10
Classifier: Programming Language :: Python :: 3.11
Classifier: Topic :: Religion
Classifier: Topic :: Software Development :: Libraries
Requires-Python: >=3.10
Requires-Dist: httpx>=0.24.0
Requires-Dist: mcp[cli]>=1.7.1
Provides-Extra: dev
Requires-Dist: pytest-asyncio>=0.21.0; extra == 'dev'
Requires-Dist: pytest>=7.0.0; extra == 'dev'
